{"TFcIjzzPTcvlkIXEPU8LnA==":"pineapple-122x122.png","pCsWOwMbNKjQC08GhCvDsg==":"mbr-1920x1280.jpg","91onSg2Iq00VCNWRMpRFPQ==":"mbr-1920x1279.jpg","D7JIkZl4sNbyRIaR9TaeNQ==":"mbr-1014x528.jpg","xzZ0m8miJhCsma1+86oB9A==":"mbr-1920x1018.jpg","R3G3nmIDJxaEnAlme7hgeg==":"shibe-meme-internet-640x484.jpg","+xGN8y2rZTHcp2QBJSeFOw==":"eh1o44icqrt01-1330x750.jpg","cf3w0si9EVmJnGjwv/Ff7A==":"e39-600x500.jpg","PtFppEZmarB+i/0gRCAOZw==":"screen_shot_2018-04-25_at_12.24.22_pm-941x544.png","aRafDMDiyDI18ErF6APgYw==":"gvr9pnc-1200x800.png","N8QqkH7JISbAsQ4oZ2hJuQ==":"21udal-400x300.jpg","kkA8Cq0F9rZ11Y6KxRv6Tw==":"bmbqwzximaafg2l-478x379.jpg","+QAR/0Q1HvXL4dWK4NNrrg==":"gvr9pnc-512x341.png","dP2OZdskV8xvc/xg8nX74g==":"dxawq2mxkaielfb-848x811.jpg","WChrPYHtPO1jhBQn+48I7w==":"logo-650x164.png","zYeuKHA6wVfMSrQJIfppsA==":"dxawq2mxkaielfb-910x870.jpg","sUijtLeLMy+jlX4t9Z76BQ==":"featmeme-618x387.jpg","sBX9dZaFTQ0EQicZD/Iupg==":"untitled-427x283.png","Q8kyWdiPLYJ/4F1Ss+9IyA==":"03.jpg","HoeEF4HfT9nMa9Cg+v0y1w==":"02.jpg","0OOE1Usrtktm437Z/qTMRQ==":"background2.jpg","Ida0uHvjKUsM36qzWIreiA==":"logo-1-650x164.png","30ApCSwUDwTK2BfT3L7HPA==":"mbr-1920x1334.jpg","wPSdwPJTyNLxNP7eZthjRA==":"mbr-1-1920x1280.jpg","g/1qt9G/oNslcqLxcczJSg==":"mbr-1920x1152.jpg","mEqdy9Y9+cNmdSEpriCi4Q==":"mbr-692x519.jpg","PMUoXThFlib/sfoZ53206A==":"mbr-952x632.jpg","zQyA7Awy+5aZaDGKscUqdA==":"mbr-1014x901.jpg","z2B+XHs6ZaYHfXlLVGF4Ow==":"mbr-1920x1275.jpg","ihlkf69UyfSmhSyJ1Jvc6w==":"jumbotron.jpg","b1MscWm8tLiDJi7Rr7fYdA==":"3a1-640x360.jpg","Mu+fzi/BQ9xqA3s1vPMXzg==":"3a1-1-640x360.jpg","9RdR0lGngAURaaPEr7ZZIA==":"mbr-1466x733.jpg","bNGTZwqi06YQK2N4AMlN5w==":"mbr-676x338.jpg","uMfcbDwGIC7uQEHlBlgEpQ==":"mbr-676x676.jpg","ZovMTlrQVcQiLDtcgD76qw==":"tgmofa1.gif","0L0pep4dwGeZW2xy0mgNCw==":"idkyimadethis-650x450.png","ycyNoGUxVWibvgBL31ltCg==":"mbr-1920x1276.jpg","hjqwiKylV5mmW5tjFGoi0Q==":"mbr-1920x1266.jpg","l7mnSAKFsi91EDGNOuEuSA==":"mbr-1920x898.jpg","gHFAvHfDwh6zxcuYs6LZDw==":"mbr-1920x1332.jpg","iDoCPM8snKAltxHr9q5tTQ==":"mbr-1920x1279.jpg","IpMvhPzNnALICOF5Qqr57A==":"mbr-1837x1920.jpg","JiRD7aKKihAJIlMpG9fYAg==":"mbr-1920x1762.jpg","fiSI12O6o+osjxxhhKu8hQ==":"mbr-1-1920x1275.jpg","6pEbp63iGyxwGvpkwPqHVw==":"mbr-1920x1080.jpg","sIyxoAw8/BTA2zDOraVcxw==":"mbr-1920x1280.jpg","INTXxMMX9KMeAKxy6oL2jQ==":"mbr-1-676x676.jpg","wF1HORX+uuilbD7Huvm+Cw==":"mbr-676x451.jpg","q5MetgSOMa9WpbNs+E1SUw==":"mbr-676x1183.jpg","U8FhZXlC5J7lq0TqL9cmBg==":"mbr-1-676x1183.jpg","0LWyMFabzPprnLEV3PQRpA==":"mbr-676x478.jpg","h8t7nkwIb/VVy3pkk3mTGw==":"mbr-1920x1281.jpg","LB1ylPMpRfuwPpsVFnvJUw==":"raxyneous%20logo-300x300.png","OTtyZQhc3z59RyKIk3fiUg==":"mbr-1-1920x1018.jpg","VMveloyPV8VEcXeiayoGlQ==":"mbr-1920x1371.jpg","QPu02gw+YQGPpGP4nqpFpw==":"df0b96d-460x456.png","d9Mvd8G+HT8OIHyssxjYDQ==":"f37bf1e-700x561.jpg","0+kvmhHhU3Vew9dT50sB0Q==":"utodvm3-700x259.jpg","40EI7nJe5CczhfhurgbdJw==":"axgaiwk-796x960.jpg","scyUeDFIOvJR8iLgeySKbA==":"cgxxkwj-640x622.jpg","TZOmNsbstWCSrnMQhHHUdA==":"how+to+recognize+a+person+you+shouldnt+fuck+with_8dd69a-6603960-1200x1558.jpg","2X+09n2XNvN62fVtatYcZg==":"mbr-1-1920x1280.jpg","HyHtGP4r392j6+KnUKZaOw==":"wr1h3wt-615x592.jpg","e0sXZNjL9BU9bYeK9TCONg==":"2c939b6-1440x1440.jpg","I2SWvm71ODEZX3bpI98osA==":"hxfr9jp-960x956.jpg","Eh/UgoQUlFAg7qUU3Jc2Jg==":"pyneappl%20cut-122x122.png","F4iShfV0LwGU2qU33EOXLQ==":"pyneappl%20cut-192x192.png","4RgVlG63SmQccRKq0jYRQQ==":"mbr-2-1920x1280.jpg","GBPfCSRFxlI0li8rdIZDyw==":"mbr-300x300.jpg","8UbI4cKZAkFL+0arCL/Wjg==":"mbr-1920x1208.jpg","tYkU+FaBMd4vHfbL2dWcjg==":"mbr-1920x1213.jpg","cm+HBUWSNtUMDihzrG3Rug==":"raxyneous%20logo-1024x1024.png","6oo5Pefp2wq3x8WjUUvl9w==":"mbr-1046x1046.jpg","G7Ds6ksYI51zhZpSXrDwTw==":"mbr-1-1920x1275-800x531.jpg","1TPZRU024bTDFZIgG/NnFw==":"mbr-1920x898-800x374.jpg","WxsQTntEqMmalyS9xwlBiQ==":"mbr-1920x1080-800x450.jpg","KF6gc0EZYbFDwDVKxqyHRw==":"mbr-1920x1776.jpg","TZTEeK+NU3rSekLfuAe2gg==":"mbr-3-1920x1280.jpg","ggb2WW1LEfo7q+0f+Y6kNg==":"mbr-1920x1440.jpg","GfPYR/jwcwb8Er5qiZij0A==":"mbr-4-1920x1280.jpg","Q3Sqa8oDZdADZveZuGVXmg==":"2018-12-15_16.42.49-720x405.png","VyuUPSDCLFIYpK5Qs8YKjQ==":"2018-12-15_03.42.54-676x380.png","UFgiaad0XG+lN75Sox8szg==":"mbr-1046x697.jpg"}